example_package/__init__.py
example_package/__main__.py
package_installation_test-1.0.0.dist-info/entry_points.txt
package_installation_test-1.0.0.dist-info/WHEEL
package_installation_test-1.0.0.dist-info/METADATA
package_installation_test-1.0.0.dist-info/RECORD
