Metadata-Version: 2.1
Name: package-installation-test
Version: 1.0.0
Summary: A test package for verifying which Python is in use and where `pip` is installing packages
Home-page: https://github.com/zahlman/package-installation-test
Keywords: test,install
Author: Karl Knechtel
Author-email: karl.a.knechtel@gmail.com
Requires-Python: >=3.8,<4.0
Classifier: Intended Audience :: Developers
Classifier: License :: OSI Approved :: The Unlicense (Unlicense)
Classifier: Programming Language :: Python :: 3
Classifier: Programming Language :: Python :: 3.8
Classifier: Programming Language :: Python :: 3.9
Classifier: Programming Language :: Python :: 3.10
Classifier: Topic :: Software Development
Project-URL: Repository, https://github.com/zahlman/package-installation-test
